Workbook

Sheet 1. Overview
A1: Section | B1: Value | C1: Unit
A2: Implementation - Total hours | B2: =SUM('2. Implementation'!D2:D100) -> 2352 | C2: h
A3: Implementation - Total cost | B3: =SUM('2. Implementation'!E2:E100) -> 2020948.6 | C3: CZK
A4: Hardware Price | B4: =SUM('3. Non-Implementation Tasks'!E2:E100) -> 1584727.2 | C4: CZK
A5: Non-Implementation Overhead Cost | B5: =SUM('4. HW Price'!D2:D100) -> 137000 | C5: CZK
A6: Annual Operating Costs | B6: =SUM('6. Yearly Payments'!B2:B100) -> 778000 | C6: CZK/yr
A7: 5-Year Total Price | B7: =(B3 + B4 + B5) + (5 * B6) -> 7632675.8 | C7: CZK

Sheet 2. Implementation
A1: Category | B1: Task | C1: Assigned To | D1: Hours | E1: Cost (CZK) | F1: Mandays
A2: Design | B2: Software Architecture (.NET MAUI) | C2: Kristián, Michal | D2: 80 | E2: =D2 * '5. Staffing Resources'!$G$10 -> 68739.75 | F2: =D2/8 -> 10 | H2: 1 MD = 8h
A3: Design | B3: UI/UX Design | C3: Jonáš, Aneta, Kristián | D3: 120 | E3: =D3 * '5. Staffing Resources'!$G$10 -> 103109.62 | F3: =D3/8 -> 15
A4: Design | B4: Initial GUI Layout (Draft) | C4: Štěpán, Ondřej | D4: 80 | E4: =D4 * '5. Staffing Resources'!$G$10 -> 68739.75 | F4: =D4/8 -> 10
A5: Design | B5: Final Graphic Mockup | C5: Štěpán, Ondřej | D5: 40 | E5: =D5 * '5. Staffing Resources'!$G$10 -> 34369.875 | F5: =D5/8 -> 5
A6: Implementation | B6: 3D Library Selection & Integration | C6: Kristián | D6: 160 | E6: =D6 * '5. Staffing Resources'!$G$10 -> 137479.5 | F6: =D6/8 -> 20
A7: Implementation | B7: DB Analysis (SQLite/JSON) | C7: Petr, Michal | D7: 64 | E7: =D7 * '5. Staffing Resources'!$G$10 -> 54991.8 | F7: =D7/8 -> 8
A8: Implementation | B8: Data Model & ER Diagram | C8: Petr, Michal | D8: 64 | E8: =D8 * '5. Staffing Resources'!$G$10 -> 54991.8 | F8: =D8/8 -> 8
A9: Implementation | B9: DB Schema Implementation | C9: Petr | D9: 40 | E9: =D9 * '5. Staffing Resources'!$G$10 -> 34369.875 | F9: =D9/8 -> 5
A10: Implementation | B10: Data Seeding (Wheelchair Components) | C10: Petr | D10: 40 | E10: =D10 * '5. Staffing Resources'!$G$10 -> 34369.875 | F10: =D10/8 -> 5
A11: Backend | B11: Component Data Models | C11: Michal | D11: 88 | E11: =D11 * '5. Staffing Resources'!$G$10 -> 75613.725 | F11: =D11/8 -> 11
A12: Backend | B12: Compatibility Rule Engine | C12: Michal | D12: 40 | E12: =D12 * '5. Staffing Resources'!$G$10 -> 34369.875 | F12: =D12/8 -> 5
A13: Backend | B13: Clinical Recommendation Logic | C13: Michal | D13: 32 | E13: =D13 * '5. Staffing Resources'!$G$10 -> 27495.9 | F13: =D13/8 -> 4
A14: Frontend | B14: UI Components & Layout | C14: Ondřej, Štěpán | D14: 104 | E14: =D14 * '5. Staffing Resources'!$G$10 -> 89361.675 | F14: =D14/8 -> 13
... A19: Testing | B19: User Acceptance Testing (FZS) | C19: Štěpán | D19: 8 | E19: =D19 * '5. Staffing Resources'!$G$10 -> 6873.975 | F19: =D19/8 -> 1
A20: TOTAL | D20: =SUM(Implementation[Hours]) -> 1176 | E20: =SUM(Implementation[Cost (CZK)]) -> 1010474.3 | F20: =SUM(Implementation[Mandays]) -> 147

Sheet 3. Non-Implementation Tasks
A1: Task | B1: Assigned To | C1: Hours | D1: Mandays | E1: Cost (CZK)
A2: Project Initialization & Setup | B2: Štěpán | C2: 24 | D2: =C2/8 -> 3 | E2: =C2 * '5. Staffing Resources'!$G$2 -> 28900.8 | G2: 1 MD = 8h
A3: Requirements Analysis & Scope | B3: Petr, Štěpán | C3: 32 | D3: =C3/8 -> 4 | E3: =C3 * '5. Staffing Resources'!$G$2 -> 38534.4
A4: Client Consultations (FZS, FDU) | B4: Štěpán, Jonáš | C4: 16 | D4: =C4/8 -> 2 | E4: =C4 * '5. Staffing Resources'!$G$2 -> 19267.2
A5: SRS Documentation | B5: Petr, Štěpán | C5: 240 | D5: =C5/8 -> 30 | E5: =C5 * '5. Staffing Resources'!$G$2 -> 289008
A6: Business Plan & WBS Creation | B6: Petr | C6: 128 | D6: =C6/8 -> 16 | E6: =C6 * '5. Staffing Resources'!$G$2 -> 154137.6
A7: Client Confirmation & Protocol | B7: Petr, Štěpán | C7: 48 | D7: =C7/8 -> 6 | E7: =C7 * '5. Staffing Resources'!$G$2 -> 57801.6
A8: Ongoing Project Management | B8: Štěpán | C8: 120 | D8: =C8/8 -> 15 | E8: =C8 * '5. Staffing Resources'!$G$2 -> 144504
A9: CI/CD & DevOps Pipeline | B9: Štěpán | C9: 50 | D9: =C9/8 -> 6.25 | E9: =C9 * '5. Staffing Resources'!$G$2 -> 60210
A10: TOTAL | C10: =SUM(Non_Implementation[Hours]) -> 658 | D10: =SUM(Non_Implementation[Mandays]) -> 82.25 | E10: =SUM(Non_Implementation[Cost (CZK)]) -> 792363.6

Sheet 4. HW Price
A1: Component | B1: Unit Price (CZK) | C1: Qty | D1: Total (CZK) | E1: Source
A2: Android Tablet 10" (ARM64, Vulkan 1.1) | B2: 9500 | C2: 5 | D2: =B2*C2 -> 47500 | E2: alza.cz
A3: Protective Case (Medical Grade) | B3: 1200 | C3: 5 | D3: =B3*C3 -> 6000 | E3: czc.cz
A4: Charging Hub / Station | B4: 3500 | C4: 2 | D4: =B4*C4 -> 7000 | E4: i-tec.pro
A5: Clinical Testing Stand | B5: 4000 | C5: 2 | D5: =B5*C5 -> 8000 | E5: ergostand.cz
A6: TOTAL | D6: =SUM(HW_Price[Total (CZK)]) -> 68500

Sheet 5. Staffing Resources
A1: Role | B1: Name | C1: Gross Salary | D1: Total Cost (+33.8%) | E1: Hourly Cost | F1: Margin (20%) | G1: Billable Rate
A2: Project Leader | B2: Štěpán Bříza | C2: 120000 | D2: =C2*1.338 -> 160560 | E2: =D2/160 -> 1003.5 | F2: =E2*0.2 -> 200.7 | G2: =E2+F2 -> 1204.2
A3: DB Master & QA | B3: Petr Chrz | C3: 80000 | D3: =C3*1.338 -> 107040 | E3: =D3/160 -> 669 | F3: =E3*0.2 -> 133.8 | G3: =E3+F3 -> 802.8
A4: Structural Engineer | B4: Kristián Kameník | C4: 95000 | D4: =C4*1.338 -> 127110 | E4: =D4/160 -> 794.4375 | F4: =E4*0.2 -> 158.8875 | G4: =E4+F4 -> 953.325
A5: Backend Developer | B5: Michal Jonáš | C5: 90000 | D5: =C5*1.338 -> 120420 | E5: =D5/160 -> 752.625 | F5: =E5*0.2 -> 150.525 | G5: =E5+F5 -> 903.15
A6: Frontend Developer | B6: Ondřej Všelko | C6: 90000 | D6: =C6*1.338 -> 120420 | E6: =D6/160 -> 752.625 | F6: =E6*0.2 -> 150.525 | G6: =E6+F6 -> 903.15
A7: UI/UX Designer | B7: Jonáš Bahner | C7: 70000 | D7: =C7*1.338 -> 93660 | E7: =D7/160 -> 585.375 | F7: =E7*0.2 -> 117.075 | G7: =E7+F7 -> 702.45
A8: 3D Modeler | B8: Aneta Smetanová | C8: 70000 | D8: =C8*1.338 -> 93660 | E8: =D8/160 -> 585.375 | F8: =E8*0.2 -> 117.075 | G8: =E8+F8 -> 702.45
A9: 3D Modeler | B9: Kristián Knap | C9: 70000 | D9: =C9*1.338 -> 93660 | E9: =D9/160 -> 585.375 | F9: =E9*0.2 -> 117.075 | G9: =E9+F9 -> 702.45
A10: AVERAGE RATE | G10: =AVERAGE(G2:G9) -> 859.24688

Sheet 6. Yearly Payments
A1: Cost Item | B1: Annual Amount (CZK)
A2: Cloud Hosting & Database Sync (Azure/AWS) | B2: 45000
A3: Maintenance & Tech Support (10h/month) | B3: 144000
A4: Legislative & MDR/GDPR Updates | B4: 80000
A5: Office Rent & Admin Overhead | B5: 120000
A6: TOTAL ANNUAL COST | B6: =SUM(B2:B5) -> 389000

Sheet 7. Business Plan
A1: Variable | B1: Meaning | C1: Value
A2: $N$ | B2: Number of configurations per year | C2: 500
A3: $T$ | B3: Time saved per configuration (hours) | C3: 2
A4: $C_h$ | B4: Therapist hourly rate (CZK/h) | C4: 1500
A5: $E$ | B5: Share of eliminated errors | C5: 0.15
A6: $C_e$ | B6: Cost of fixing one manual error | C6: 5000
A7: V | B7: Total Annual Social Value | C7: =(C2*C3*C4)+(C2*C5*C6) -> 1875000
A8: P | B8: Annual License Fee (10% Value Capture) | C8: =C7*0.1 -> 187500
